lo2/__init__.py
lo2/__main__.py
lo2/lo2cmd.py
lo2/plugins/__init__.py
lo2/plugins/plot/__init__.py
lo2/plugins/plot/heatmap.py
lo2/plugins/plot/linear.py
lo2/src/Exception.py
lo2/src/__init__.py
lo2/src/lo2html.py
lo2/src/lo2json.py
lo2/src/lo2lang.py
lo2/src/lo2log.py
lo2/src/lo2parser.py
lo2/src/lo2print.py
lo2/src/lo2state.py
lo2/src/lo2text.py
lo2/src/logoracle.py
lo2/src/parsetab.py
lo2/src/test.py
lo2/src/utils.py
lo2-0.5.4.dist-info/METADATA
lo2-0.5.4.dist-info/WHEEL
lo2-0.5.4.dist-info/top_level.txt
lo2-0.5.4.dist-info/RECORD
