Metadata-Version: 2.1
Name: lo2
Version: 0.5.4
Summary: lo2 - Log Oracle, an Oracle test language for log description and analysis
Author: DUHP BSP Team
Author-email: zhangte01@baidu.com
Requires-Dist: Jinja2 ==3.1.2
Requires-Dist: ply >=3
Requires-Dist: chardet >=2.0
Requires-Dist: matplotlib >=3.5
